nk_sent2vec/__init__.py
nk_sent2vec/config.py
nk_sent2vec/embed.py
nk_sent2vec/tests.py
nk_sent2vec-1.4.2.dist-info/LICENSE
nk_sent2vec-1.4.2.dist-info/METADATA
nk_sent2vec-1.4.2.dist-info/WHEEL
nk_sent2vec-1.4.2.dist-info/top_level.txt
nk_sent2vec-1.4.2.dist-info/RECORD
