Metadata-Version: 2.1
Name: nk-sent2vec
Version: 1.4.2
Summary: Embeds text documents using sent2vec
Home-page: UNKNOWN
Author: New Knowledge
License: BSD-3-Clause
Platform: UNKNOWN
Requires-Dist: Cython (==0.29.24)
Requires-Dist: numpy (>=1.15.4)
Requires-Dist: pytest
Requires-Dist: sent2vec (<0.3,>=0.2)
